pygame_dashboard/Dashboard.py
pygame_dashboard/__init__.py
pygame_dashboard/dashdraw.py
pygame_dashboard-0.0.1.dist-info/DESCRIPTION.rst
pygame_dashboard-0.0.1.dist-info/METADATA
pygame_dashboard-0.0.1.dist-info/RECORD
pygame_dashboard-0.0.1.dist-info/WHEEL
pygame_dashboard-0.0.1.dist-info/metadata.json
pygame_dashboard-0.0.1.dist-info/top_level.txt
