Metadata-Version: 2.0
Name: pygame-dashboard
Version: 0.0.1
Summary: Simples elements of Dashboard from PyGame
Home-page: https://github.com/brunosantanaa/pygame-dashboard
Author: Bruno Santana
Author-email: bruno.sant.a@gmail.com
License: MIT
Platform: UNKNOWN
